[
  {
    "id" : 1,
    "title" : "幸福",
    "data" : "2019-3-27 19:08:56",
    "count" : 1
  },
  {
    "id" : 2,
    "title" : "幸福",
    "data" : "2019-3-27 19:08:56",
    "count" : 1
  },{
    "id" : 3,
    "title" : "幸福",
    "data" : "2019-3-27 19:08:56",
    "count" : 2
  },{
    "id" : 4,
    "title" : "幸福",
    "data" : "2019-3-27 19:08:56",
    "count" : 1
  },{
    "id" : 5,
    "title" : "真好",
    "data" : "2019-3-27 19:08:56",
    "count" : 1
  },{
    "id" : 6,
    "title" : "震惊震惊",
    "data" : "2019-3-27 19:08:56",
    "count" : 3
  },{
    "id" : 7,
    "title" : "幸福",
    "data" : "2019-3-27 19:08:56",
    "count" : 1
  },{
    "id" : 8,
    "title" : "幸福",
    "data" : "2019-3-27 19:08:56",
    "count" : 1
  },{
    "id" : 9,
    "title" : "幸福",
    "data" : "2019-3-27 19:08:56",
    "count" : 1
  },{
    "id" : 10,
    "title" : "幸福",
    "data" : "2019-3-27 19:08:56",
    "count" : 1
  }

]
